astonish/__init__.py
astonish/globals.py
astonish/logo.py
astonish/main.py
astonish/agents/agents_creator.yaml
astonish/core/__init__.py
astonish/core/agent_runner.py
astonish/core/error_handler.py
astonish/core/format_handler.py
astonish/core/graph_builder.py
astonish/core/json_utils.py
astonish/core/llm_manager.py
astonish/core/mcp_manager.py
astonish/core/node_functions.py
astonish/core/output_model_utils.py
astonish/core/prompt_templates.py
astonish/core/react_planning.py
astonish/core/state_management.py
astonish/core/ui_utils.py
astonish/core/utils.py
astonish/factory/__init__.py
astonish/factory/ai_provider_factory.py
astonish/providers/__init__.py
astonish/providers/ai_provider_interface.py
astonish/providers/anthropic_provider.py
astonish/providers/exceptions.py
astonish/providers/google_genai_provider.py
astonish/providers/groq_provider.py
astonish/providers/lm_studio_provider.py
astonish/providers/ollama_provider.py
astonish/providers/openai_provider.py
astonish/providers/openrouter_provider.py
astonish/providers/sap_ai_core_provider.py
astonish/tools/__init__.py
astonish/tools/internal_tools.py
astonish/tools/mcp_config_editor.py
astonish/tools/tool_base.py
astonish-0.12.5.dist-info/licenses/LICENSE
astonish-0.12.5.dist-info/METADATA
astonish-0.12.5.dist-info/WHEEL
astonish-0.12.5.dist-info/entry_points.txt
astonish-0.12.5.dist-info/top_level.txt
astonish-0.12.5.dist-info/RECORD
