Metadata-Version: 2.4
Name: astonish
Version: 0.12.5
Summary: Astonish AI Companion
Author-email: Rafael Schardosin Silva <rafael.rs@gmail.com>
Project-URL: Homepage, https://github.com/schardosin/astonish
Classifier: Programming Language :: Python :: 3
Classifier: License :: OSI Approved :: MIT License
Classifier: Operating System :: OS Independent
Requires-Python: >=3.9
License-File: LICENSE
Requires-Dist: appdirs==1.4.4
Requires-Dist: sap-ai-sdk-gen[all]==5.4.2
Requires-Dist: langchain-ollama==0.3.1
Requires-Dist: langchain==0.3.26
Requires-Dist: langgraph==0.5.0
Requires-Dist: langgraph-checkpoint-sqlite==2.0.6
Requires-Dist: langchain-mcp-adapters==0.0.9
Requires-Dist: aiosqlite==0.21.0
Requires-Dist: grandalf==0.8
Requires-Dist: pykwalify==1.8.0
Requires-Dist: inquirer==3.4.0
Requires-Dist: langchain-anthropic==0.3.16
Requires-Dist: langchain-google-genai==2.1.5
Requires-Dist: rich==14.0.0
Requires-Dist: unidiff==0.7.5
Requires-Dist: json5==0.12.0
Provides-Extra: test
Requires-Dist: pytest==8.3.5; extra == "test"
Requires-Dist: pytest-asyncio==0.26.0; extra == "test"
Dynamic: license-file
